pypgcdc/__init__.py
pypgcdc/__main__.py
pypgcdc/decoders.py
pypgcdc/models.py
pypgcdc/reader.py
pypgcdc/stores.py
pypgcdc/utils.py
python_postgres_cdc-0.0.0rc2.dist-info/LICENSE
python_postgres_cdc-0.0.0rc2.dist-info/METADATA
python_postgres_cdc-0.0.0rc2.dist-info/WHEEL
python_postgres_cdc-0.0.0rc2.dist-info/entry_points.txt
python_postgres_cdc-0.0.0rc2.dist-info/top_level.txt
python_postgres_cdc-0.0.0rc2.dist-info/RECORD
