Metadata-Version: 2.1
Name: python-postgres-cdc
Version: 0.0.0rc2
Summary: Change Data Capture (CDC) library for Postgres
Author-email: Roman Kutlak <roman@kutlak.net>
License: MIT License
Project-URL: Homepage, https://github.com/roman-kutlak/pypgcdc
Keywords: postgres,CDC,change,data,capture,logical,replication,outbox
Classifier: License :: OSI Approved :: MIT License
Classifier: Programming Language :: Python
Classifier: Programming Language :: Python :: 3
Classifier: Topic :: Database
Classifier: Topic :: System
Classifier: Topic :: System :: Archiving
Classifier: Topic :: System :: Archiving :: Mirroring
Requires-Python: >=3.7
License-File: LICENSE
Requires-Dist: psycopg2-binary >=2.8.0
Requires-Dist: pydantic >=1.10.0
Provides-Extra: dev
Requires-Dist: black ; extra == 'dev'
Requires-Dist: pip-tools ; extra == 'dev'
Requires-Dist: pytest ; extra == 'dev'
Requires-Dist: build ; extra == 'dev'
Requires-Dist: twine ; extra == 'dev'
